morpho/__version__.py
morpho/cli.py
morpho/client.py
morpho/config.py
morpho/consumer.py
morpho/error.py
morpho/log.py
morpho/rest/__init__.py
morpho/rest/models.py
morpho/rest/models.pyi
morpho/rest/raw.py
morpho/rest/swagger/.swagger-codegen/VERSION
morpho/rest/swagger/.swagger-codegen-ignore
morpho/rest/swagger/README.md
morpho/rest/swagger/openapi.yaml
morpho/server.py
morpho/types.py
morpho/util.py
morpho-1.0.0b8.dist-info/entry_points.txt
morpho-1.0.0b8.dist-info/LICENSE
morpho-1.0.0b8.dist-info/WHEEL
morpho-1.0.0b8.dist-info/METADATA
morpho-1.0.0b8.dist-info/RECORD
