Metadata-Version: 2.1
Name: morpho
Version: 1.0.0b8
Summary: A framework for microservice based document transformation.
Home-page: https://python-morpho.org/
License: MIT
Keywords: microservice,distributed-systems,transform,metamorphosis
Author: B4rtware
Author-email: 34386047+B4rtware@users.noreply.github.com
Requires-Python: >=3.8,<4.0
Classifier: License :: OSI Approved :: MIT License
Classifier: Programming Language :: Python :: 3
Classifier: Programming Language :: Python :: 3.8
Requires-Dist: colorama (>=0.4.3,<0.5.0)
Requires-Dist: flask (>=1.1.1,<2.0.0)
Requires-Dist: py-eureka-client (>=0.7.4,<0.8.0)
Requires-Dist: pydantic (>=1.5.1,<2.0.0)
Requires-Dist: regex (>=2020.6.7,<2021.0.0)
Requires-Dist: requests (>=2.22.0,<3.0.0)
Requires-Dist: toml (>=0.10.0,<0.11.0)
Requires-Dist: waitress (>=1.4.2,<2.0.0)
Project-URL: Repository, https://github.com/B4rtware/morpho
